[
  {
    "id": "f1f8246937134de7acd6d40f",
    "originalName": "HackedPodcast.jpg",
    "fileName": "m9c3rt4z-a7fd4a5e2e99fa242df73b4.jpg",
    "mimeType": "image/jpeg",
    "size": 298528,
    "uploadedAt": "2025-04-11T01:23:01.778Z",
    "metadata": {
      "width": 1920,
      "height": 1080,
      "format": "jpg"
    },
    "views": 0,
    "downloads": 2
  },
  {
    "id": "8fee89d9ec4cf676a4d9dc5f",
    "originalName": "blockedpage-pepita.gif",
    "fileName": "m9c3u6mz-defe5cf5f3477fd751e18be.gif",
    "mimeType": "image/gif",
    "size": 424558,
    "uploadedAt": "2025-04-11T01:24:52.717Z",
    "metadata": {
      "width": 1920,
      "height": 1080,
      "format": "gif"
    },
    "views": 0,
    "downloads": 1
  }
]